README.rst
setup.cfg
setup.py
acton/__init__.py
acton/acton.py
acton/cli.py
acton/database.py
acton/kde_predictor.py
acton/labellers.py
acton/plot.py
acton/predictors.py
acton/recommenders.py
acton.egg-info/PKG-INFO
acton.egg-info/SOURCES.txt
acton.egg-info/dependency_links.txt
acton.egg-info/entry_points.txt
acton.egg-info/not-zip-safe
acton.egg-info/top_level.txt