Metadata-Version: 1.1
Name: acton
Version: 0.3.1
Summary: A scientific research assistant
Home-page: https://github.com/chengsoonong/acton
Author: Cheng Soon Ong
Author-email: chengsoon.ong@anu.edu.au
License: BSD license
Keywords: machine-learning active-learning classification regression
Platform: UNKNOWN
Classifier: Development Status :: 2 - Pre-Alpha
Classifier: Intended Audience :: Science/Research
Classifier: Topic :: Scientific/Engineering
Classifier: License :: OSI Approved :: BSD License
Classifier: Natural Language :: English
Classifier: Programming Language :: Python :: 3
Classifier: Programming Language :: Python :: 3.4
Classifier: Programming Language :: Python :: 3.5
